{".class":"MypyFile","_fullname":"Medical_KG.briefing.qa","future_import_flags":["annotations"],"is_partial_stub_package":false,"is_stub":false,"names":{".class":"SymbolTable","Citation":{".class":"SymbolTableNode","cross_ref":"Medical_KG.briefing.models.Citation","kind":"Gdef","module_hidden":true,"module_public":false},"Evidence":{".class":"SymbolTableNode","cross_ref":"Medical_KG.briefing.models.Evidence","kind":"Gdef","module_hidden":true,"module_public":false},"IntentRouter":{".class":"SymbolTableNode","kind":"Gdef","node":{".class":"TypeInfo","_promote":[],"abstract_attributes":[],"alt_promote":null,"bases":["builtins.object"],"dataclass_transform_spec":null,"declared_metaclass":null,"defn":{".class":"ClassDef","fullname":"Medical_KG.briefing.qa.IntentRouter","name":"IntentRouter","type_vars":[]},"deletable_attributes":[],"deprecated":null,"flags":[],"fullname":"Medical_KG.briefing.qa.IntentRouter","has_param_spec_type":false,"metaclass_type":null,"metadata":{},"module_name":"Medical_KG.briefing.qa","mro":["Medical_KG.briefing.qa.IntentRouter","builtins.object"],"names":{".class":"SymbolTable","route":{".class":"SymbolTableNode","kind":"Mdef","node":{".class":"FuncDef","abstract_status":0,"arg_kinds":[0,0],"arg_names":["self","query"],"dataclass_transform_spec":null,"deprecated":null,"flags":[],"fullname":"Medical_KG.briefing.qa.IntentRouter.route","name":"route","type":{".class":"CallableType","arg_kinds":[0,0],"arg_names":["self","query"],"arg_types":["Medical_KG.briefing.qa.IntentRouter","builtins.str"],"bound_args":[],"def_extras":{"first_arg":"self"},"fallback":"builtins.function","from_concatenate":false,"implicit":false,"imprecise_arg_kinds":false,"is_ellipsis_args":false,"name":"route of IntentRouter","ret_type":"builtins.str","type_guard":null,"type_is":null,"unpack_kwargs":false,"variables":[]}}}},"self_type":{".class":"TypeVarType","default":{".class":"AnyType","missing_import_name":null,"source_any":null,"type_of_any":4},"fullname":"Medical_KG.briefing.qa.IntentRouter.Self","id":0,"name":"Self","namespace":"","upper_bound":"Medical_KG.briefing.qa.IntentRouter","values":[],"variance":0},"slots":null,"tuple_type":null,"type_vars":[],"typeddict_type":null}},"Iterable":{".class":"SymbolTableNode","cross_ref":"typing.Iterable","kind":"Gdef","module_hidden":true,"module_public":false},"Mapping":{".class":"SymbolTableNode","cross_ref":"typing.Mapping","kind":"Gdef","module_hidden":true,"module_public":false},"QAEngine":{".class":"SymbolTableNode","kind":"Gdef","node":{".class":"TypeInfo","_promote":[],"abstract_attributes":[],"alt_promote":null,"bases":["builtins.object"],"dataclass_transform_spec":null,"declared_metaclass":null,"defn":{".class":"ClassDef","fullname":"Medical_KG.briefing.qa.QAEngine","name":"QAEngine","type_vars":[]},"deletable_attributes":[],"deprecated":null,"flags":[],"fullname":"Medical_KG.briefing.qa.QAEngine","has_param_spec_type":false,"metaclass_type":null,"metadata":{},"module_name":"Medical_KG.briefing.qa","mro":["Medical_KG.briefing.qa.QAEngine","builtins.object"],"names":{".class":"SymbolTable","__init__":{".class":"SymbolTableNode","kind":"Mdef","node":{".class":"FuncDef","abstract_status":0,"arg_kinds":[0,1],"arg_names":["self","router"],"dataclass_transform_spec":null,"deprecated":null,"flags":[],"fullname":"Medical_KG.briefing.qa.QAEngine.__init__","name":"__init__","type":{".class":"CallableType","arg_kinds":[0,1],"arg_names":["self","router"],"arg_types":["Medical_KG.briefing.qa.QAEngine",{".class":"UnionType","items":["Medical_KG.briefing.qa.IntentRouter",{".class":"NoneType"}],"uses_pep604_syntax":true}],"bound_args":[],"def_extras":{"first_arg":"self"},"fallback":"builtins.function","from_concatenate":false,"implicit":false,"imprecise_arg_kinds":false,"is_ellipsis_args":false,"name":"__init__ of QAEngine","ret_type":{".class":"NoneType"},"type_guard":null,"type_is":null,"unpack_kwargs":false,"variables":[]}}},"_format_conflict":{".class":"SymbolTableNode","kind":"Mdef","node":{".class":"FuncDef","abstract_status":0,"arg_kinds":[0,0],"arg_names":["self","evidences"],"dataclass_transform_spec":null,"deprecated":null,"flags":[],"fullname":"Medical_KG.briefing.qa.QAEngine._format_conflict","name":"_format_conflict","type":{".class":"CallableType","arg_kinds":[0,0],"arg_names":["self","evidences"],"arg_types":["Medical_KG.briefing.qa.QAEngine",{".class":"Instance","args":["Medical_KG.briefing.models.Evidence"],"extra_attrs":null,"type_ref":"typing.Sequence"}],"bound_args":[],"def_extras":{"first_arg":"self"},"fallback":"builtins.function","from_concatenate":false,"implicit":false,"imprecise_arg_kinds":false,"is_ellipsis_args":false,"name":"_format_conflict of QAEngine","ret_type":{".class":"Instance","args":["builtins.str","builtins.object"],"extra_attrs":null,"type_ref":"typing.Mapping"},"type_guard":null,"type_is":null,"unpack_kwargs":false,"variables":[]}}},"_format_evidence":{".class":"SymbolTableNode","kind":"Mdef","node":{".class":"FuncDef","abstract_status":0,"arg_kinds":[0,0],"arg_names":["self","evidence"],"dataclass_transform_spec":null,"deprecated":null,"flags":[],"fullname":"Medical_KG.briefing.qa.QAEngine._format_evidence","name":"_format_evidence","type":{".class":"CallableType","arg_kinds":[0,0],"arg_names":["self","evidence"],"arg_types":["Medical_KG.briefing.qa.QAEngine","Medical_KG.briefing.models.Evidence"],"bound_args":[],"def_extras":{"first_arg":"self"},"fallback":"builtins.function","from_concatenate":false,"implicit":false,"imprecise_arg_kinds":false,"is_ellipsis_args":false,"name":"_format_evidence of QAEngine","ret_type":{".class":"Instance","args":["builtins.str","builtins.object"],"extra_attrs":null,"type_ref":"typing.Mapping"},"type_guard":null,"type_is":null,"unpack_kwargs":false,"variables":[]}}},"_format_generic":{".class":"SymbolTableNode","kind":"Mdef","node":{".class":"FuncDef","abstract_status":0,"arg_kinds":[0,0,0],"arg_names":["self","text","citations"],"dataclass_transform_spec":null,"deprecated":null,"flags":[],"fullname":"Medical_KG.briefing.qa.QAEngine._format_generic","name":"_format_generic","type":{".class":"CallableType","arg_kinds":[0,0,0],"arg_names":["self","text","citations"],"arg_types":["Medical_KG.briefing.qa.QAEngine","builtins.str",{".class":"Instance","args":["Medical_KG.briefing.models.Citation"],"extra_attrs":null,"type_ref":"typing.Sequence"}],"bound_args":[],"def_extras":{"first_arg":"self"},"fallback":"builtins.function","from_concatenate":false,"implicit":false,"imprecise_arg_kinds":false,"is_ellipsis_args":false,"name":"_format_generic of QAEngine","ret_type":{".class":"Instance","args":["builtins.str","builtins.object"],"extra_attrs":null,"type_ref":"typing.Mapping"},"type_guard":null,"type_is":null,"unpack_kwargs":false,"variables":[]}}},"_router":{".class":"SymbolTableNode","implicit":true,"kind":"Mdef","node":{".class":"Var","flags":["is_inferred"],"fullname":"Medical_KG.briefing.qa.QAEngine._router","name":"_router","type":"Medical_KG.briefing.qa.IntentRouter"}},"_summarize_effect":{".class":"SymbolTableNode","kind":"Mdef","node":{".class":"FuncDef","abstract_status":0,"arg_kinds":[0,0],"arg_names":["self","evidences"],"dataclass_transform_spec":null,"deprecated":null,"flags":[],"fullname":"Medical_KG.briefing.qa.QAEngine._summarize_effect","name":"_summarize_effect","type":{".class":"CallableType","arg_kinds":[0,0],"arg_names":["self","evidences"],"arg_types":["Medical_KG.briefing.qa.QAEngine",{".class":"Instance","args":["Medical_KG.briefing.models.Evidence"],"extra_attrs":null,"type_ref":"typing.Sequence"}],"bound_args":[],"def_extras":{"first_arg":"self"},"fallback":"builtins.function","from_concatenate":false,"implicit":false,"imprecise_arg_kinds":false,"is_ellipsis_args":false,"name":"_summarize_effect of QAEngine","ret_type":"builtins.str","type_guard":null,"type_is":null,"unpack_kwargs":false,"variables":[]}}},"_summarize_items":{".class":"SymbolTableNode","kind":"Mdef","node":{".class":"FuncDef","abstract_status":0,"arg_kinds":[0,0,3],"arg_names":["self","items","field"],"dataclass_transform_spec":null,"deprecated":null,"flags":[],"fullname":"Medical_KG.briefing.qa.QAEngine._summarize_items","name":"_summarize_items","type":{".class":"CallableType","arg_kinds":[0,0,3],"arg_names":["self","items","field"],"arg_types":["Medical_KG.briefing.qa.QAEngine",{".class":"Instance","args":["builtins.object"],"extra_attrs":null,"type_ref":"typing.Sequence"},"builtins.str"],"bound_args":[],"def_extras":{"first_arg":"self"},"fallback":"builtins.function","from_concatenate":false,"implicit":false,"imprecise_arg_kinds":false,"is_ellipsis_args":false,"name":"_summarize_items of QAEngine","ret_type":"builtins.str","type_guard":null,"type_is":null,"unpack_kwargs":false,"variables":[]}}},"answer":{".class":"SymbolTableNode","kind":"Mdef","node":{".class":"FuncDef","abstract_status":0,"arg_kinds":[0,0,0],"arg_names":["self","query","bundle"],"dataclass_transform_spec":null,"deprecated":null,"flags":[],"fullname":"Medical_KG.briefing.qa.QAEngine.answer","name":"answer","type":{".class":"CallableType","arg_kinds":[0,0,0],"arg_names":["self","query","bundle"],"arg_types":["Medical_KG.briefing.qa.QAEngine","builtins.str","Medical_KG.briefing.models.TopicBundle"],"bound_args":[],"def_extras":{"first_arg":"self"},"fallback":"builtins.function","from_concatenate":false,"implicit":false,"imprecise_arg_kinds":false,"is_ellipsis_args":false,"name":"answer of QAEngine","ret_type":"Medical_KG.briefing.qa.QAResult","type_guard":null,"type_is":null,"unpack_kwargs":false,"variables":[]}}}},"self_type":{".class":"TypeVarType","default":{".class":"AnyType","missing_import_name":null,"source_any":null,"type_of_any":4},"fullname":"Medical_KG.briefing.qa.QAEngine.Self","id":0,"name":"Self","namespace":"","upper_bound":"Medical_KG.briefing.qa.QAEngine","values":[],"variance":0},"slots":null,"tuple_type":null,"type_vars":[],"typeddict_type":null}},"QAResult":{".class":"SymbolTableNode","kind":"Gdef","node":{".class":"TypeInfo","_promote":[],"abstract_attributes":[],"alt_promote":null,"bases":["builtins.object"],"dataclass_transform_spec":null,"declared_metaclass":null,"defn":{".class":"ClassDef","fullname":"Medical_KG.briefing.qa.QAResult","name":"QAResult","type_vars":[]},"deletable_attributes":[],"deprecated":null,"flags":[],"fullname":"Medical_KG.briefing.qa.QAResult","has_param_spec_type":false,"metaclass_type":null,"metadata":{"dataclass":{"attributes":[{"alias":null,"column":4,"has_default":false,"is_in_init":true,"is_init_var":false,"is_neither_frozen_nor_nonfrozen":false,"kw_only":false,"line":13,"name":"answer","type":"builtins.str"},{"alias":null,"column":4,"has_default":false,"is_in_init":true,"is_init_var":false,"is_neither_frozen_nor_nonfrozen":false,"kw_only":false,"line":14,"name":"intent","type":"builtins.str"},{"alias":null,"column":4,"has_default":false,"is_in_init":true,"is_init_var":false,"is_neither_frozen_nor_nonfrozen":false,"kw_only":false,"line":15,"name":"evidence","type":{".class":"Instance","args":[{".class":"Instance","args":["builtins.str","builtins.object"],"extra_attrs":null,"type_ref":"typing.Mapping"}],"extra_attrs":null,"type_ref":"typing.Sequence"}},{"alias":null,"column":4,"has_default":false,"is_in_init":true,"is_init_var":false,"is_neither_frozen_nor_nonfrozen":false,"kw_only":false,"line":16,"name":"conflicts","type":{".class":"Instance","args":[{".class":"Instance","args":["builtins.str","builtins.object"],"extra_attrs":null,"type_ref":"typing.Mapping"}],"extra_attrs":null,"type_ref":"typing.Sequence"}},{"alias":null,"column":4,"has_default":false,"is_in_init":true,"is_init_var":false,"is_neither_frozen_nor_nonfrozen":false,"kw_only":false,"line":17,"name":"gaps","type":{".class":"Instance","args":["builtins.str"],"extra_attrs":null,"type_ref":"typing.Sequence"}}],"frozen":true},"dataclass_tag":{}},"module_name":"Medical_KG.briefing.qa","mro":["Medical_KG.briefing.qa.QAResult","builtins.object"],"names":{".class":"SymbolTable","__dataclass_fields__":{".class":"SymbolTableNode","kind":"Mdef","node":{".class":"Var","flags":["is_classvar","is_ready"],"fullname":"Medical_KG.briefing.qa.QAResult.__dataclass_fields__","name":"__dataclass_fields__","type":{".class":"Instance","args":["builtins.str",{".class":"Instance","args":[{".class":"AnyType","missing_import_name":null,"source_any":null,"type_of_any":2}],"extra_attrs":null,"type_ref":"dataclasses.Field"}],"extra_attrs":null,"type_ref":"builtins.dict"}},"plugin_generated":true},"__init__":{".class":"SymbolTableNode","kind":"Mdef","node":{".class":"FuncDef","abstract_status":0,"arg_kinds":[0,0,0,0,0,0],"arg_names":["self","answer","intent","evidence","conflicts","gaps"],"dataclass_transform_spec":null,"deprecated":null,"flags":[],"fullname":"Medical_KG.briefing.qa.QAResult.__init__","name":"__init__","type":{".class":"CallableType","arg_kinds":[0,0,0,0,0,0],"arg_names":["self","answer","intent","evidence","conflicts","gaps"],"arg_types":["Medical_KG.briefing.qa.QAResult","builtins.str","builtins.str",{".class":"Instance","args":[{".class":"Instance","args":["builtins.str","builtins.object"],"extra_attrs":null,"type_ref":"typing.Mapping"}],"extra_attrs":null,"type_ref":"typing.Sequence"},{".class":"Instance","args":[{".class":"Instance","args":["builtins.str","builtins.object"],"extra_attrs":null,"type_ref":"typing.Mapping"}],"extra_attrs":null,"type_ref":"typing.Sequence"},{".class":"Instance","args":["builtins.str"],"extra_attrs":null,"type_ref":"typing.Sequence"}],"bound_args":[],"def_extras":{},"fallback":"builtins.function","from_concatenate":false,"implicit":false,"imprecise_arg_kinds":false,"is_ellipsis_args":false,"name":"__init__ of QAResult","ret_type":{".class":"NoneType"},"type_guard":null,"type_is":null,"unpack_kwargs":false,"variables":[]}},"plugin_generated":true},"__match_args__":{".class":"SymbolTableNode","kind":"Mdef","node":{".class":"Var","flags":["is_ready","allow_incompatible_override"],"fullname":"Medical_KG.briefing.qa.QAResult.__match_args__","name":"__match_args__","type":{".class":"TupleType","implicit":false,"items":[{".class":"LiteralType","fallback":"builtins.str","value":"answer"},{".class":"LiteralType","fallback":"builtins.str","value":"intent"},{".class":"LiteralType","fallback":"builtins.str","value":"evidence"},{".class":"LiteralType","fallback":"builtins.str","value":"conflicts"},{".class":"LiteralType","fallback":"builtins.str","value":"gaps"}],"partial_fallback":{".class":"Instance","args":[{".class":"AnyType","missing_import_name":null,"source_any":null,"type_of_any":6}],"extra_attrs":null,"type_ref":"builtins.tuple"}}},"plugin_generated":true},"__mypy-replace":{".class":"SymbolTableNode","kind":"Mdef","node":{".class":"Decorator","func":{".class":"FuncDef","abstract_status":0,"arg_kinds":[5,5,5,5,5],"arg_names":["answer","intent","evidence","conflicts","gaps"],"dataclass_transform_spec":null,"deprecated":null,"flags":["is_static","is_decorated"],"fullname":"Medical_KG.briefing.qa.QAResult.__mypy-replace","name":"__mypy-replace","type":{".class":"CallableType","arg_kinds":[5,5,5,5,5],"arg_names":["answer","intent","evidence","conflicts","gaps"],"arg_types":["builtins.str","builtins.str",{".class":"Instance","args":[{".class":"Instance","args":["builtins.str","builtins.object"],"extra_attrs":null,"type_ref":"typing.Mapping"}],"extra_attrs":null,"type_ref":"typing.Sequence"},{".class":"Instance","args":[{".class":"Instance","args":["builtins.str","builtins.object"],"extra_attrs":null,"type_ref":"typing.Mapping"}],"extra_attrs":null,"type_ref":"typing.Sequence"},{".class":"Instance","args":["builtins.str"],"extra_attrs":null,"type_ref":"typing.Sequence"}],"bound_args":[],"def_extras":{},"fallback":"builtins.function","from_concatenate":false,"implicit":false,"imprecise_arg_kinds":false,"is_ellipsis_args":false,"name":"__mypy-replace of QAResult","ret_type":{".class":"NoneType"},"type_guard":null,"type_is":null,"unpack_kwargs":false,"variables":[]}},"is_overload":false,"var":{".class":"Var","flags":["is_staticmethod","is_ready"],"fullname":"Medical_KG.briefing.qa.QAResult.__mypy-replace","name":"__mypy-replace","type":{".class":"CallableType","arg_kinds":[5,5,5,5,5],"arg_names":["answer","intent","evidence","conflicts","gaps"],"arg_types":["builtins.str","builtins.str",{".class":"Instance","args":[{".class":"Instance","args":["builtins.str","builtins.object"],"extra_attrs":null,"type_ref":"typing.Mapping"}],"extra_attrs":null,"type_ref":"typing.Sequence"},{".class":"Instance","args":[{".class":"Instance","args":["builtins.str","builtins.object"],"extra_attrs":null,"type_ref":"typing.Mapping"}],"extra_attrs":null,"type_ref":"typing.Sequence"},{".class":"Instance","args":["builtins.str"],"extra_attrs":null,"type_ref":"typing.Sequence"}],"bound_args":[],"def_extras":{},"fallback":"builtins.function","from_concatenate":false,"implicit":false,"imprecise_arg_kinds":false,"is_ellipsis_args":false,"name":"__mypy-replace of QAResult","ret_type":{".class":"NoneType"},"type_guard":null,"type_is":null,"unpack_kwargs":false,"variables":[]}}},"plugin_generated":true},"__slots__":{".class":"SymbolTableNode","kind":"Mdef","node":{".class":"Var","flags":["is_ready","allow_incompatible_override"],"fullname":"Medical_KG.briefing.qa.QAResult.__slots__","name":"__slots__","type":{".class":"TupleType","implicit":false,"items":["builtins.str","builtins.str","builtins.str","builtins.str","builtins.str"],"partial_fallback":{".class":"Instance","args":[{".class":"AnyType","missing_import_name":null,"source_any":null,"type_of_any":6}],"extra_attrs":null,"type_ref":"builtins.tuple"}}},"plugin_generated":true},"answer":{".class":"SymbolTableNode","implicit":true,"kind":"Mdef","node":{".class":"Var","flags":["is_initialized_in_class","is_property","is_ready"],"fullname":"Medical_KG.briefing.qa.QAResult.answer","name":"answer","type":"builtins.str"}},"conflicts":{".class":"SymbolTableNode","implicit":true,"kind":"Mdef","node":{".class":"Var","flags":["is_initialized_in_class","is_property","is_ready"],"fullname":"Medical_KG.briefing.qa.QAResult.conflicts","name":"conflicts","type":{".class":"Instance","args":[{".class":"Instance","args":["builtins.str","builtins.object"],"extra_attrs":null,"type_ref":"typing.Mapping"}],"extra_attrs":null,"type_ref":"typing.Sequence"}}},"evidence":{".class":"SymbolTableNode","implicit":true,"kind":"Mdef","node":{".class":"Var","flags":["is_initialized_in_class","is_property","is_ready"],"fullname":"Medical_KG.briefing.qa.QAResult.evidence","name":"evidence","type":{".class":"Instance","args":[{".class":"Instance","args":["builtins.str","builtins.object"],"extra_attrs":null,"type_ref":"typing.Mapping"}],"extra_attrs":null,"type_ref":"typing.Sequence"}}},"gaps":{".class":"SymbolTableNode","implicit":true,"kind":"Mdef","node":{".class":"Var","flags":["is_initialized_in_class","is_property","is_ready"],"fullname":"Medical_KG.briefing.qa.QAResult.gaps","name":"gaps","type":{".class":"Instance","args":["builtins.str"],"extra_attrs":null,"type_ref":"typing.Sequence"}}},"intent":{".class":"SymbolTableNode","implicit":true,"kind":"Mdef","node":{".class":"Var","flags":["is_initialized_in_class","is_property","is_ready"],"fullname":"Medical_KG.briefing.qa.QAResult.intent","name":"intent","type":"builtins.str"}}},"self_type":{".class":"TypeVarType","default":{".class":"AnyType","missing_import_name":null,"source_any":null,"type_of_any":4},"fullname":"Medical_KG.briefing.qa.QAResult.Self","id":0,"name":"Self","namespace":"","upper_bound":"Medical_KG.briefing.qa.QAResult","values":[],"variance":0},"slots":["answer","conflicts","evidence","gaps","intent"],"tuple_type":null,"type_vars":[],"typeddict_type":null}},"Sequence":{".class":"SymbolTableNode","cross_ref":"typing.Sequence","kind":"Gdef","module_hidden":true,"module_public":false},"TopicBundle":{".class":"SymbolTableNode","cross_ref":"Medical_KG.briefing.models.TopicBundle","kind":"Gdef","module_hidden":true,"module_public":false},"__all__":{".class":"SymbolTableNode","kind":"Gdef","module_public":false,"node":{".class":"Var","flags":["is_inferred","has_explicit_value"],"fullname":"Medical_KG.briefing.qa.__all__","name":"__all__","type":{".class":"Instance","args":["builtins.str"],"extra_attrs":null,"type_ref":"builtins.list"}}},"__annotations__":{".class":"SymbolTableNode","kind":"Gdef","module_public":false,"node":{".class":"Var","flags":["is_ready"],"fullname":"Medical_KG.briefing.qa.__annotations__","name":"__annotations__","type":{".class":"Instance","args":["builtins.str",{".class":"AnyType","missing_import_name":null,"source_any":null,"type_of_any":6}],"extra_attrs":null,"type_ref":"builtins.dict"}}},"__doc__":{".class":"SymbolTableNode","kind":"Gdef","module_public":false,"node":{".class":"Var","flags":["is_ready"],"fullname":"Medical_KG.briefing.qa.__doc__","name":"__doc__","type":"builtins.str"}},"__file__":{".class":"SymbolTableNode","kind":"Gdef","module_public":false,"node":{".class":"Var","flags":["is_ready"],"fullname":"Medical_KG.briefing.qa.__file__","name":"__file__","type":"builtins.str"}},"__name__":{".class":"SymbolTableNode","kind":"Gdef","module_public":false,"node":{".class":"Var","flags":["is_ready"],"fullname":"Medical_KG.briefing.qa.__name__","name":"__name__","type":"builtins.str"}},"__package__":{".class":"SymbolTableNode","kind":"Gdef","module_public":false,"node":{".class":"Var","flags":["is_ready"],"fullname":"Medical_KG.briefing.qa.__package__","name":"__package__","type":"builtins.str"}},"__spec__":{".class":"SymbolTableNode","kind":"Gdef","module_public":false,"node":{".class":"Var","flags":["is_ready"],"fullname":"Medical_KG.briefing.qa.__spec__","name":"__spec__","type":"_frozen_importlib.ModuleSpec"}},"_find_conflicting_effects":{".class":"SymbolTableNode","kind":"Gdef","module_public":false,"node":{".class":"FuncDef","abstract_status":0,"arg_kinds":[0],"arg_names":["evidences"],"dataclass_transform_spec":null,"deprecated":null,"flags":[],"fullname":"Medical_KG.briefing.qa._find_conflicting_effects","name":"_find_conflicting_effects","type":{".class":"CallableType","arg_kinds":[0],"arg_names":["evidences"],"arg_types":[{".class":"Instance","args":["Medical_KG.briefing.models.Evidence"],"extra_attrs":null,"type_ref":"typing.Iterable"}],"bound_args":[],"def_extras":{"first_arg":null},"fallback":"builtins.function","from_concatenate":false,"implicit":false,"imprecise_arg_kinds":false,"is_ellipsis_args":false,"name":"_find_conflicting_effects","ret_type":{".class":"Instance","args":[{".class":"Instance","args":["Medical_KG.briefing.models.Evidence"],"extra_attrs":null,"type_ref":"builtins.list"}],"extra_attrs":null,"type_ref":"builtins.list"},"type_guard":null,"type_is":null,"unpack_kwargs":false,"variables":[]}}},"_find_gaps":{".class":"SymbolTableNode","kind":"Gdef","module_public":false,"node":{".class":"FuncDef","abstract_status":0,"arg_kinds":[0,0],"arg_names":["bundle","intent"],"dataclass_transform_spec":null,"deprecated":null,"flags":[],"fullname":"Medical_KG.briefing.qa._find_gaps","name":"_find_gaps","type":{".class":"CallableType","arg_kinds":[0,0],"arg_names":["bundle","intent"],"arg_types":["Medical_KG.briefing.models.TopicBundle","builtins.str"],"bound_args":[],"def_extras":{"first_arg":null},"fallback":"builtins.function","from_concatenate":false,"implicit":false,"imprecise_arg_kinds":false,"is_ellipsis_args":false,"name":"_find_gaps","ret_type":{".class":"Instance","args":["builtins.str"],"extra_attrs":null,"type_ref":"builtins.list"},"type_guard":null,"type_is":null,"unpack_kwargs":false,"variables":[]}}},"annotations":{".class":"SymbolTableNode","cross_ref":"__future__.annotations","kind":"Gdef","module_hidden":true,"module_public":false},"dataclass":{".class":"SymbolTableNode","cross_ref":"dataclasses.dataclass","kind":"Gdef","module_hidden":true,"module_public":false}},"path":"/home/paul/Medical_KG/src/Medical_KG/briefing/qa.py"}