{"data_mtime":1759519429,"dep_lines":[25,28,23,27,26,27,15,16,17,18,19,21,22,1,1,1,1,1,1,1,1,1,1,1,1,1,1,1,1,1,1,1,1,1,1,1,1,1,1,1,1],"dep_prios":[5,5,5,10,5,5,10,10,5,5,5,10,5,5,20,30,30,30,30,30,30,30,30,30,30,30,30,30,30,30,30,30,30,30,30,30,30,30,30,30,30],"dependencies":["transformers.models.auto.modeling_auto","transformers.data.processors.squad","torch.utils.data","transformers.utils.logging","transformers.tokenization_utils","transformers.utils","os","time","dataclasses","enum","typing","torch","filelock","builtins","multiprocessing.reduction","_collections_abc","_frozen_importlib","abc","collections","contextlib","filelock._api","filelock._soft","genericpath","logging","posixpath","torch._C","torch._tensor","torch.serialization","torch.types","torch.utils","torch.utils.data.dataset","transformers.configuration_utils","transformers.data.processors","transformers.data.processors.utils","transformers.models","transformers.models.auto","transformers.models.auto.auto_factory","transformers.tokenization_utils_base","transformers.utils.hub","transformers.utils.import_utils","types"],"hash":"00bd31fa58011f3e91b81bc401cf249f26e52c44","id":"transformers.data.datasets.squad","ignore_all":true,"interface_hash":"a570c5b3c72feb6c3c1e3d75461e86ebb8d7e9e9","mtime":1759417128,"options":{"allow_redefinition":false,"allow_untyped_globals":false,"always_false":[],"always_true":[],"bazel":false,"check_untyped_defs":true,"disable_bytearray_promotion":false,"disable_error_code":[],"disable_memoryview_promotion":false,"disabled_error_codes":[],"disallow_any_decorated":false,"disallow_any_explicit":false,"disallow_any_expr":false,"disallow_any_generics":true,"disallow_any_unimported":false,"disallow_incomplete_defs":true,"disallow_subclassing_any":true,"disallow_untyped_calls":true,"disallow_untyped_decorators":true,"disallow_untyped_defs":true,"enable_error_code":[],"enabled_error_codes":[],"extra_checks":true,"follow_imports":"normal","follow_imports_for_stubs":false,"follow_untyped_imports":false,"ignore_errors":false,"ignore_missing_imports":false,"implicit_optional":false,"implicit_reexport":false,"local_partial_types":false,"mypyc":false,"old_type_inference":false,"platform":"linux","plugins":[],"strict_bytes":false,"strict_concatenate":false,"strict_equality":true,"strict_optional":true,"warn_no_return":true,"warn_return_any":true,"warn_unreachable":false,"warn_unused_ignores":true},"path":"/home/paul/Medical_KG/.venv/lib/python3.12/site-packages/transformers/data/datasets/squad.py","plugin_data":null,"size":9295,"suppressed":[],"version_id":"1.15.0"}